fasthep_cli/__init__.py
fasthep_cli/_download.py
fasthep_cli/_plotter.py
fasthep_cli/_software.py
fasthep_cli/logo.py
fasthep_cli/main.py
fasthep_cli/py.typed
fasthep_cli-0.1.2.dist-info/entry_points.txt
fasthep_cli-0.1.2.dist-info/WHEEL
fasthep_cli-0.1.2.dist-info/METADATA
fasthep_cli-0.1.2.dist-info/RECORD
