Metadata-Version: 2.1
Name: fasthep_cli
Version: 0.1.2
Summary: A command line interface for the FAST-HEP tools (one to rule them all)
Author-email: Luke Kreczko <fast-hep@cern.ch>
Maintainer-email: The FAST-HEP maintainers <fast-hep@cern.ch>
Requires-Python: >=3.8
Classifier: License :: OSI Approved :: BSD License
Classifier: Topic :: Scientific/Engineering
Classifier: Intended Audience :: Science/Research
Classifier: Intended Audience :: Developers
Classifier: Operating System :: OS Independent
Classifier: License :: OSI Approved :: Apache Software License
Classifier: Programming Language :: Python
Classifier: Programming Language :: Python :: 3
Classifier: Programming Language :: Python :: 3.8
Classifier: Programming Language :: Python :: 3.9
Classifier: Programming Language :: Python :: 3.10
Classifier: Development Status :: 1 - Planning
Requires-Dist: mplhep
Requires-Dist: PyYAML
Requires-Dist: requests
Requires-Dist: rich
Requires-Dist: tabulate
Requires-Dist: typer
Requires-Dist: pytest >=6 ; extra == "dev"
Requires-Dist: Sphinx>=4.0 ; extra == "docs"
Requires-Dist: myst_parser>=0.13 ; extra == "docs"
Requires-Dist: sphinx-book-theme>=0.1.0 ; extra == "docs"
Requires-Dist: sphinx_copybutton ; extra == "docs"
Requires-Dist: pytest >=6 ; extra == "test"
Project-URL: homepage, https://github.com/FAST-HEP/fasthep-cli
Provides-Extra: dev
Provides-Extra: docs
Provides-Extra: test
